{
  "GridXSize": 35,
  "GridYSize": 30,
  "Arrows": [
    {
      "Indices": [
        226,
        227,
        228,
        193,
        194
      ],
      "ColorIndex": 8
    },
    {
      "Indices": [
        18,
        17,
        16,
        51,
        50,
        85,
        84,
        119,
        154,
        155,
        156
      ],
      "ColorIndex": 9
    },
    {
      "Indices": [
        52,
        53,
        88,
        123,
        124
      ],
      "ColorIndex": 4
    },
    {
      "Indices": [
        122,
        87,
        86,
        121,
        120
      ],
      "ColorIndex": 2
    },
    {
      "Indices": [
        54,
        89,
        90,
        125,
        160,
        159,
        158,
        157,
        192,
        191,
        190
      ],
      "ColorIndex": 7
    },
    {
      "Indices": [
        266,
        301,
        300,
        299,
        334,
        333,
        332,
        331,
        330,
        295,
        294,
        293,
        258
      ],
      "ColorIndex": 7
    },
    {
      "Indices": [
        326,
        361,
        362,
        363,
        328,
        327,
        292
      ],
      "ColorIndex": 5
    },
    {
      "Indices": [
        474,
        473,
        472,
        471,
        470,
        435,
        434,
        469,
        468
      ],
      "ColorIndex": 2
    },
    {
      "Indices": [
        408,
        407,
        442,
        441,
        440,
        475
      ],
      "ColorIndex": 5
    },
    {
      "Indices": [
        406,
        371,
        336,
        337,
        372,
        373
      ],
      "ColorIndex": 1
    },
    {
      "Indices": [
        436,
        437,
        438,
        439,
        404,
        405,
        370,
        335
      ],
      "ColorIndex": 2
    },
    {
      "Indices": [
        369,
        368,
        403,
        402,
        367
      ],
      "ColorIndex": 6
    },
    {
      "Indices": [
        400,
        401,
        366,
        365
      ],
      "ColorIndex": 3
    },
    {
      "Indices": [
        329,
        364,
        399,
        398,
        433,
        432,
        397,
        396,
        395
      ],
      "ColorIndex": 8
    },
    {
      "Indices": [
        674,
        675,
        676,
        641,
        606,
        571,
        536,
        535,
        500,
        499,
        534,
        533,
        568,
        567,
        532,
        497,
        498,
        463
      ],
      "ColorIndex": 3
    },
    {
      "Indices": [
        531,
        566,
        565
      ],
      "ColorIndex": 2
    },
    {
      "Indices": [
        569,
        570,
        605,
        640,
        639,
        604,
        603,
        638,
        637,
        602,
        601
      ],
      "ColorIndex": 6
    },
    {
      "Indices": [
        677,
        642,
        607,
        572,
        537
      ],
      "ColorIndex": 0
    },
    {
      "Indices": [
        588,
        553,
        552,
        517,
        516,
        481
      ],
      "ColorIndex": 4
    },
    {
      "Indices": [
        515,
        550,
        585,
        620,
        621,
        622,
        587,
        586,
        551
      ],
      "ColorIndex": 9
    },
    {
      "Indices": [
        722,
        687,
        652,
        617,
        582,
        547,
        548,
        583,
        618,
        619,
        584,
        549,
        514
      ],
      "ColorIndex": 1
    },
    {
      "Indices": [
        690,
        689,
        688,
        723
      ],
      "ColorIndex": 9
    },
    {
      "Indices": [
        653,
        654,
        655,
        656
      ],
      "ColorIndex": 7
    },
    {
      "Indices": [
        616,
        615,
        580,
        581
      ],
      "ColorIndex": 4
    },
    {
      "Indices": [
        648,
        683,
        718,
        753,
        752,
        717,
        682,
        647
      ],
      "ColorIndex": 3
    },
    {
      "Indices": [
        721,
        720,
        719,
        754,
        755,
        756
      ],
      "ColorIndex": 4
    },
    {
      "Indices": [
        684,
        649,
        650,
        685,
        686,
        651
      ],
      "ColorIndex": 5
    },
    {
      "Indices": [
        645,
        646,
        681,
        680,
        715,
        716,
        751,
        750
      ],
      "ColorIndex": 0
    },
    {
      "Indices": [
        610,
        611,
        612,
        613,
        614
      ],
      "ColorIndex": 1
    },
    {
      "Indices": [
        749,
        714,
        679,
        644,
        609,
        574
      ],
      "ColorIndex": 6
    },
    {
      "Indices": [
        710,
        711,
        712,
        713,
        748
      ],
      "ColorIndex": 9
    },
    {
      "Indices": [
        573,
        608,
        643,
        678
      ],
      "ColorIndex": 7
    },
    {
      "Indices": [
        806,
        771,
        770,
        735,
        736,
        701,
        702,
        667,
        668,
        633
      ],
      "ColorIndex": 4
    },
    {
      "Indices": [
        777,
        776,
        775,
        774,
        773,
        808,
        843,
        842,
        807,
        772,
        737
      ],
      "ColorIndex": 8
    },
    {
      "Indices": [
        669,
        704,
        705,
        740,
        741
      ],
      "ColorIndex": 5
    },
    {
      "Indices": [
        703,
        738,
        739
      ],
      "ColorIndex": 7
    },
    {
      "Indices": [
        848,
        883,
        918,
        917,
        916,
        915,
        880,
        845,
        810,
        809,
        844,
        879,
        878
      ],
      "ColorIndex": 3
    },
    {
      "Indices": [
        881,
        882,
        847,
        846,
        811,
        812
      ],
      "ColorIndex": 4
    },
    {
      "Indices": [
        952,
        953,
        954,
        919,
        884,
        849,
        814,
        813,
        778
      ],
      "ColorIndex": 1
    },
    {
      "Indices": [
        850,
        885,
        920,
        955,
        990,
        989
      ],
      "ColorIndex": 3
    },
    {
      "Indices": [
        853,
        888,
        923,
        922,
        921,
        886,
        887,
        852,
        851
      ],
      "ColorIndex": 8
    },
    {
      "Indices": [
        1035,
        1034,
        1033,
        1032,
        1031,
        1030,
        1029,
        1028,
        993,
        958,
        957,
        992,
        991,
        956
      ],
      "ColorIndex": 7
    },
    {
      "Indices": [
        994,
        995,
        996,
        997,
        962,
        961,
        960,
        959
      ],
      "ColorIndex": 9
    },
    {
      "Indices": [
        998,
        963,
        928,
        893,
        892,
        927,
        926,
        891,
        890,
        925,
        924,
        889
      ],
      "ColorIndex": 7
    },
    {
      "Indices": [
        1005,
        970,
        969,
        1004,
        1003,
        1002,
        1001,
        1036
      ],
      "ColorIndex": 8
    },
    {
      "Indices": [
        929,
        930,
        965,
        964,
        999,
        1000
      ],
      "ColorIndex": 6
    },
    {
      "Indices": [
        863,
        862,
        897,
        932,
        967,
        966,
        931,
        896,
        861,
        860,
        895,
        894
      ],
      "ColorIndex": 0
    },
    {
      "Indices": [
        901,
        936,
        935,
        934,
        899,
        898,
        933,
        968
      ],
      "ColorIndex": 8
    },
    {
      "Indices": [
        729,
        764,
        799,
        834,
        869,
        868,
        867,
        866,
        831,
        830,
        829,
        864,
        865,
        900
      ],
      "ColorIndex": 3
    },
    {
      "Indices": [
        833,
        832,
        797,
        798,
        763
      ],
      "ColorIndex": 5
    },
    {
      "Indices": [
        661,
        696,
        731,
        766,
        765,
        730,
        695
      ],
      "ColorIndex": 8
    },
    {
      "Indices": [
        769,
        768,
        733,
        732,
        697
      ],
      "ColorIndex": 5
    },
    {
      "Indices": [
        767,
        802,
        803,
        804
      ],
      "ColorIndex": 7
    },
    {
      "Indices": [
        871,
        870,
        835,
        800,
        801,
        836,
        837
      ],
      "ColorIndex": 6
    },
    {
      "Indices": [
        902,
        937,
        972,
        971
      ],
      "ColorIndex": 7
    },
    {
      "Indices": [
        938,
        903,
        904,
        905
      ],
      "ColorIndex": 5
    }
  ]
}